<class name="ssl">
  SSL properties for a connection.

  <link relation="amqp" href="http://docs.oasis-open.org/amqp/core/v1.0/os/amqp-core-security-v1.0-os.html#section-tls">Conceptual overview</link>

  <!--
  <property name="verify-mode"></property>
  <property name="resume-status"></property>
  -->
</class>

<!--
<class name="ssl-client-options">
  SSL configuration for outbound connections.
</class>

<class name="ssl-server-options">
  SSL configuration for inbound connections.
</class>
-->
